autocoder_rag_sdk/__init__.py
autocoder_rag_sdk/client.py
autocoder_rag_sdk/models.py
autocoder_rag_sdk/utils.py
autocoder_rag_sdk-0.0.2.dist-info/METADATA
autocoder_rag_sdk-0.0.2.dist-info/WHEEL
autocoder_rag_sdk-0.0.2.dist-info/licenses/LICENSE
autocoder_rag_sdk-0.0.2.dist-info/RECORD
