Metadata-Version: 2.4
Name: autocoder-rag-sdk
Version: 0.0.2
Summary: Python SDK for AutoCoder RAG - 便于在Python代码中调用auto-coder.rag run功能
Project-URL: Homepage, https://github.com/allwefantasy/auto-coder
Project-URL: Documentation, https://github.com/allwefantasy/auto-coder/tree/master/rag-sdks/python
Project-URL: Repository, https://github.com/allwefantasy/auto-coder
Project-URL: Bug Tracker, https://github.com/allwefantasy/auto-coder/issues
Author-email: AutoCoder Team <support@autocoder.com>
Maintainer-email: AutoCoder Team <support@autocoder.com>
License: MIT License
License-File: LICENSE
Keywords: ai,api,autocoder,document-qa,python,rag,sdk
Classifier: Development Status :: 4 - Beta
Classifier: Intended Audience :: Developers
Classifier: License :: OSI Approved :: MIT License
Classifier: Programming Language :: Python :: 3.10
Classifier: Programming Language :: Python :: 3.11
Classifier: Programming Language :: Python :: 3.12
Classifier: Topic :: Software Development :: Code Generators
Classifier: Topic :: Software Development :: Libraries :: Python Modules
Classifier: Topic :: Utilities
Requires-Python: >=3.10
Requires-Dist: typing-extensions>=3.7.4; python_version < '3.8'
Provides-Extra: dev
Requires-Dist: black>=21.0.0; extra == 'dev'
Requires-Dist: isort>=5.0.0; extra == 'dev'
Requires-Dist: pytest-asyncio>=0.18.0; extra == 'dev'
Requires-Dist: pytest>=6.0.0; extra == 'dev'
